{"Area":["\u25A0\u25A0\u25A0\u25A0\u25A0\u25A0\u25A0\u25A0\u25A0\u25A0\u25A0\u25A0\u25A0\u25A0\u25A0\u25A0\u25A0\u25A0\u25A0\u25A0\u25A0","\u25A0\u25A0\u25A0\u25A0\u25A0\u25A0\u25A0\u25A0\u25A0\u25A0\u25A0\u25A0\u25A0\u25A0\u25A0\u25A0\u25A0\u25A0\u25A0\u25A0\u25A0","\u25A0\u25A0\u25A0\u25A0\u25A0\u25A0\u25A0\u25A0\u25A0\u25A0\u25A0\u25A0\u25A0\u25A0\u25A0\u25A0\u25A0\u25A0\u25A0\u25A0\u25A0","\u25A0\u25A0\u25A0\u25A0\u25A0\u25A0\u25A0\u25A0\u25A0\u25A0\u25A0\u25A0\u25A0\u25A0\u25A0\u25A0\u25A0\u25A0\u25A0\u25A0\u25A0","\u25A0\u25A0\u25A0\u25A0\u25A0\u25A0\u25A0\u25A0\u25A0\u25A0\u25A0\u25A0\u25A0\u25A0\u25A0\u25A0\u25A0\u25A0\u25A0\u25A0\u25A0","                     ","                     ","                     ","                     ","                     ","                     ","                     ","                     ","                     ","      \u25CF              ","                     ","                     ","                     ","                     ","          \u2580\u2580\u2580        "],"BallX":6,"BallY":14,"PlatX":10,"PlatY":19,"Difficulty":"HARD"}